{
  "main": {
    "id": "b121e6e866ee127d",
    "type": "split",
    "children": [
      {
        "id": "cbd25abbaad29178",
        "type": "tabs",
        "children": [
          {
            "id": "396c8b244016b02c",
            "type": "leaf",
            "state": {
              "type": "markdown",
              "state": {
                "file": "Linux/Полезные утилиты Linux и Fix-ы.md",
                "mode": "source",
                "source": false
              },
              "icon": "lucide-file",
              "title": "Полезные утилиты Linux и Fix-ы"
            }
          }
        ]
      }
    ],
    "direction": "vertical"
  },
  "left": {
    "id": "a8c1c48b5af1801d",
    "type": "split",
    "children": [
      {
        "id": "0160f422783e97bb",
        "type": "tabs",
        "children": [
          {
            "id": "17fed151ed0190ff",
            "type": "leaf",
            "state": {
              "type": "file-explorer",
              "state": {
                "sortOrder": "alphabetical",
                "autoReveal": false
              },
              "icon": "lucide-folder-closed",
              "title": "Файловый менеджер"
            }
          },
          {
            "id": "ed857ce8f2e71757",
            "type": "leaf",
            "state": {
              "type": "search",
              "state": {
                "query": "",
                "matchingCase": false,
                "explainSearch": false,
                "collapseAll": false,
                "extraContext": false,
                "sortOrder": "alphabetical"
              },
              "icon": "lucide-search",
              "title": "Поиск"
            }
          },
          {
            "id": "3e1df315b906f944",
            "type": "leaf",
            "state": {
              "type": "bookmarks",
              "state": {},
              "icon": "lucide-bookmark",
              "title": "Закладки"
            }
          }
        ]
      }
    ],
    "direction": "horizontal",
    "width": 300
  },
  "right": {
    "id": "d9ec1f1d08b34c8a",
    "type": "split",
    "children": [
      {
        "id": "dc9f271801c8c812",
        "type": "tabs",
        "children": [
          {
            "id": "46185e1f4328b737",
            "type": "leaf",
            "state": {
              "type": "backlink",
              "state": {
                "file": "7 способов восстановить удаленные файлыВосстановалениеDjccnБез.md",
                "collapseAll": false,
                "extraContext": false,
                "sortOrder": "alphabetical",
                "showSearch": false,
                "searchQuery": "",
                "backlinkCollapsed": false,
                "unlinkedCollapsed": true
              },
              "icon": "links-coming-in",
              "title": "Обратные ссылки для 7 способов восстановить удаленные файлыВосстановалениеDjccnБез"
            }
          },
          {
            "id": "8a371f8ebb069539",
            "type": "leaf",
            "state": {
              "type": "outgoing-link",
              "state": {
                "file": "7 способов восстановить удаленные файлыВосстановалениеDjccnБез.md",
                "linksCollapsed": false,
                "unlinkedCollapsed": true
              },
              "icon": "links-going-out",
              "title": "Исходящие ссылки из 7 способов восстановить удаленные файлыВосстановалениеDjccnБез"
            }
          },
          {
            "id": "93647c3dc76cbfb3",
            "type": "leaf",
            "state": {
              "type": "tag",
              "state": {
                "sortOrder": "frequency",
                "useHierarchy": true,
                "showSearch": false,
                "searchQuery": ""
              },
              "icon": "lucide-tags",
              "title": "Теги"
            }
          },
          {
            "id": "2c75e17047dde714",
            "type": "leaf",
            "state": {
              "type": "all-properties",
              "state": {
                "sortOrder": "frequency",
                "showSearch": false,
                "searchQuery": ""
              },
              "icon": "lucide-archive",
              "title": "Все свойства"
            }
          },
          {
            "id": "ca38831e613ace75",
            "type": "leaf",
            "state": {
              "type": "outline",
              "state": {
                "file": "7 способов восстановить удаленные файлыВосстановалениеDjccnБез.md",
                "followCursor": false,
                "showSearch": false,
                "searchQuery": ""
              },
              "icon": "lucide-list",
              "title": "Структура 7 способов восстановить удаленные файлыВосстановалениеDjccnБез"
            }
          }
        ]
      }
    ],
    "direction": "horizontal",
    "width": 300,
    "collapsed": true
  },
  "left-ribbon": {
    "hiddenItems": {
      "switcher:Меню быстрого перехода": false,
      "graph:Граф": false,
      "canvas:Создать новый холст": false,
      "daily-notes:Сегодняшняя заметка": false,
      "templates:Вставить шаблон": false,
      "command-palette:Открыть палитру команд": false,
      "bases:Создать новую базу": false
    }
  },
  "active": "396c8b244016b02c",
  "lastOpenFiles": [
    "Бобро обжаловать.md",
    "Linux/Полезные утилиты Linux и Fix-ы.md",
    "Linux/Черный экран Steam в Niri.md",
    "Linux/Obsidian в Linux.md",
    "Linux/Архивы .7z в Linux.md",
    "Linux/Lazygit в Linux.md",
    "Learn/Освоение VIM..md",
    "Learn",
    "Linux/Восстановить удаленные файлы.md",
    "Linux/Настройка SSH в Linux.md",
    "Linux/Dotfiles в CashyOS + Niri.md",
    "Linux/Терминал Kitty.md",
    "Настройка.md",
    "Learn/Рассуждения по дистрибутивам.md",
    "Linux",
    "создайте ссылку.md"
  ]
}